{
  "displayWeekday": "Thursday",
  "displayDate": "November 08, 2018",
  "printDate": "2018-11-08",
  "centerLetter": "b",
  "outerLetters": [
    "a",
    "c",
    "l",
    "n",
    "o",
    "y"
  ],
  "validLetters": [
    "b",
    "a",
    "c",
    "l",
    "n",
    "o",
    "y"
  ],
  "pangrams": [
    "balcony"
  ],
  "answers": [
    "abbacy",
    "ably",
    "baba",
    "baboon",
    "baby",
    "bacon",
    "balcony",
    "ball",
    "ballboy",
    "balloon",
    "banal",
    "banally",
    "banana",
    "banc",
    "banyan",
    "baobab",
    "blab",
    "blabby",
    "blob",
    "blobby",
    "bloc",
    "boba",
    "bola",
    "boll",
    "bolo",
    "bonbon",
    "bonny",
    "bonobo",
    "bony",
    "boob",
    "booboo",
    "booby",
    "boon",
    "cabal",
    "cabala",
    "cabana",
    "cabby",
    "cannonball",
    "lobby",
    "lobo",
    "nabob",
    "nobly",
    "noob"
  ],
  "id": 1541653200,
  "freeExpiration": 0,
  "editor": "Sam Ezersky"
}