{
  "displayWeekday": "Sunday",
  "displayDate": "August 19, 2018",
  "printDate": "2018-08-19",
  "centerLetter": "t",
  "outerLetters": [
    "c",
    "f",
    "i",
    "n",
    "o",
    "r"
  ],
  "validLetters": [
    "t",
    "c",
    "f",
    "i",
    "n",
    "o",
    "r"
  ],
  "pangrams": [
    "friction"
  ],
  "answers": [
    "citric",
    "citron",
    "concoct",
    "concoction",
    "confit",
    "confront",
    "contort",
    "contortion",
    "contrition",
    "coot",
    "cotton",
    "critic",
    "fiction",
    "finito",
    "font",
    "foot",
    "fort",
    "friction",
    "front",
    "into",
    "intro",
    "nitric",
    "nitro",
    "nonfiction",
    "notion",
    "onto",
    "rift",
    "riot",
    "root",
    "roti",
    "roto",
    "rotor",
    "tiff",
    "tinct",
    "tint",
    "tonic",
    "toon",
    "toot",
    "tori",
    "toric",
    "torii",
    "torn",
    "toro",
    "tort",
    "tortoni",
    "tricorn",
    "tricot",
    "trio",
    "triton",
    "trot"
  ],
  "id": 1534651200,
  "freeExpiration": 0,
  "editor": "Sam Ezersky"
}