{
  "displayWeekday": "Monday",
  "displayDate": "September 09, 2019",
  "printDate": "2019-09-09",
  "centerLetter": "a",
  "outerLetters": [
    "b",
    "c",
    "k",
    "l",
    "o",
    "w"
  ],
  "validLetters": [
    "a",
    "b",
    "c",
    "k",
    "l",
    "o",
    "w"
  ],
  "pangrams": [
    "blowback"
  ],
  "answers": [
    "aback",
    "alack",
    "allow",
    "baba",
    "babka",
    "back",
    "balk",
    "ball",
    "baobab",
    "bawl",
    "blab",
    "black",
    "blackball",
    "blowback",
    "boba",
    "bola",
    "cabal",
    "cabala",
    "cacao",
    "call",
    "calla",
    "callaloo",
    "callback",
    "callow",
    "clack",
    "claw",
    "cloaca",
    "cloak",
    "coal",
    "coca",
    "cocoa",
    "cola",
    "kabob",
    "koala",
    "kola",
    "lack",
    "lawbook",
    "local",
    "lowball",
    "wack",
    "wacko",
    "walk",
    "wall",
    "wallow"
  ],
  "id": 1568001600,
  "freeExpiration": 0,
  "editor": "Sam Ezersky"
}