{
  "displayWeekday": "Thursday",
  "displayDate": "September 26, 2019",
  "printDate": "2019-09-26",
  "centerLetter": "w",
  "outerLetters": [
    "a",
    "d",
    "k",
    "l",
    "r",
    "y"
  ],
  "validLetters": [
    "w",
    "a",
    "d",
    "k",
    "l",
    "r",
    "y"
  ],
  "pangrams": [
    "awkwardly"
  ],
  "answers": [
    "award",
    "away",
    "awkward",
    "awkwardly",
    "awry",
    "draw",
    "drawl",
    "drawly",
    "drywall",
    "layaway",
    "rawly",
    "walk",
    "walkway",
    "wall",
    "ward",
    "wary",
    "waylay",
    "wayward",
    "waywardly",
    "wryly",
    "yawl"
  ],
  "id": 1569470400,
  "freeExpiration": 0,
  "editor": "Sam Ezersky"
}