{
  "displayWeekday": "Friday",
  "displayDate": "January 17, 2020",
  "printDate": "2020-01-17",
  "centerLetter": "o",
  "outerLetters": [
    "g",
    "h",
    "l",
    "n",
    "r",
    "u"
  ],
  "validLetters": [
    "o",
    "g",
    "h",
    "l",
    "n",
    "r",
    "u"
  ],
  "pangrams": [
    "hourlong"
  ],
  "answers": [
    "ghoul",
    "gong",
    "googol",
    "goon",
    "gorgon",
    "grog",
    "honor",
    "horn",
    "horror",
    "hour",
    "hourlong",
    "logo",
    "logroll",
    "loll",
    "long",
    "longhorn",
    "loon",
    "noon",
    "noun",
    "oolong",
    "roll",
    "rough",
    "unroll"
  ],
  "id": 1579237200,
  "freeExpiration": 0,
  "editor": "Sam Ezersky"
}