{
  "displayWeekday": "Tuesday",
  "displayDate": "September 28, 2021",
  "printDate": "2021-09-28",
  "centerLetter": "o",
  "outerLetters": [
    "c",
    "d",
    "e",
    "i",
    "j",
    "n"
  ],
  "validLetters": [
    "o",
    "c",
    "d",
    "e",
    "i",
    "j",
    "n"
  ],
  "pangrams": [
    "conjoined"
  ],
  "answers": [
    "cocci",
    "cocoon",
    "cocooned",
    "code",
    "coded",
    "codeine",
    "codon",
    "coed",
    "coin",
    "coincide",
    "coincided",
    "coincidence",
    "coined",
    "concede",
    "conceded",
    "condo",
    "condone",
    "condoned",
    "cone",
    "coned",
    "conic",
    "conjoin",
    "conjoined",
    "conned",
    "cooed",
    "deco",
    "decode",
    "decoded",
    "dino",
    "diode",
    "dodo",
    "dojo",
    "done",
    "donee",
    "donned",
    "ecocide",
    "encode",
    "encoded",
    "enjoin",
    "enjoined",
    "icon",
    "iconic",
    "innocence",
    "iodine",
    "ionic",
    "join",
    "joined",
    "neocon",
    "neon",
    "nodded",
    "node",
    "nonce",
    "none",
    "noon",
    "odeon",
    "once",
    "onion"
  ],
  "id": 1632801600,
  "freeExpiration": 0,
  "editor": "Sam Ezersky"
}