{
  "displayWeekday": "Wednesday",
  "displayDate": "September 15, 2021",
  "printDate": "2021-09-15",
  "centerLetter": "i",
  "outerLetters": [
    "a",
    "d",
    "l",
    "n",
    "o",
    "r"
  ],
  "validLetters": [
    "i",
    "a",
    "d",
    "l",
    "n",
    "o",
    "r"
  ],
  "pangrams": [
    "doornail",
    "ordinal"
  ],
  "answers": [
    "aioli",
    "andiron",
    "android",
    "anion",
    "aria",
    "arid",
    "aril",
    "dial",
    "dildo",
    "dill",
    "dinar",
    "dino",
    "dirndl",
    "doornail",
    "drain",
    "drill",
    "droid",
    "idol",
    "indoor",
    "inlaid",
    "inland",
    "inroad",
    "iron",
    "laid",
    "lain",
    "lair",
    "lanai",
    "lanolin",
    "liar",
    "lion",
    "lira",
    "loin",
    "nadir",
    "naiad",
    "nail",
    "noir",
    "nonillion",
    "olio",
    "onion",
    "ordain",
    "ordinal",
    "radial",
    "radian",
    "radii",
    "radio",
    "raid",
    "rail",
    "railroad",
    "rain",
    "rani",
    "rial",
    "rill",
    "rind",
    "roil"
  ],
  "id": 1631678400,
  "freeExpiration": 0,
  "editor": "Sam Ezersky"
}