{
  "displayWeekday": "Wednesday",
  "displayDate": "January 26, 2022",
  "printDate": "2022-01-26",
  "centerLetter": "l",
  "outerLetters": [
    "a",
    "f",
    "i",
    "n",
    "p",
    "t"
  ],
  "validLetters": [
    "l",
    "a",
    "f",
    "i",
    "n",
    "p",
    "t"
  ],
  "pangrams": [
    "flippant",
    "plaintiff"
  ],
  "answers": [
    "alfalfa",
    "alit",
    "anal",
    "annal",
    "appall",
    "atilt",
    "fail",
    "fall",
    "fantail",
    "fatal",
    "filial",
    "fill",
    "fillip",
    "final",
    "finial",
    "flail",
    "flan",
    "flap",
    "flat",
    "flint",
    "flip",
    "flippant",
    "flit",
    "infill",
    "initial",
    "lain",
    "lanai",
    "lantana",
    "lift",
    "lilt",
    "lint",
    "nail",
    "natal",
    "pail",
    "palapa",
    "palatal",
    "palatial",
    "pall",
    "palp",
    "papal",
    "papilla",
    "pilaf",
    "pill",
    "pintail",
    "pitfall",
    "plain",
    "plaint",
    "plaintiff",
    "plait",
    "plan",
    "plant",
    "plantain",
    "plat",
    "pliant",
    "tail",
    "tailfin",
    "tali",
    "tall",
    "tallit",
    "tilapia",
    "till",
    "tilt"
  ],
  "id": 1643173200,
  "freeExpiration": 0,
  "editor": "Sam Ezersky"
}