{
  "displayWeekday": "Wednesday",
  "displayDate": "February 09, 2022",
  "printDate": "2022-02-09",
  "centerLetter": "g",
  "outerLetters": [
    "a",
    "d",
    "n",
    "r",
    "u",
    "v"
  ],
  "validLetters": [
    "g",
    "a",
    "d",
    "n",
    "r",
    "u",
    "v"
  ],
  "pangrams": [
    "vanguard"
  ],
  "answers": [
    "agar",
    "augur",
    "dang",
    "drag",
    "drug",
    "dung",
    "durag",
    "gaga",
    "gang",
    "grad",
    "gran",
    "grand",
    "grandad",
    "granddad",
    "guar",
    "guard",
    "guava",
    "guru",
    "raga",
    "rang",
    "rung",
    "vanguard"
  ],
  "id": 1644382800,
  "freeExpiration": 0,
  "editor": "Sam Ezersky"
}