{
  "displayWeekday": "Tuesday",
  "displayDate": "November 15, 2022",
  "printDate": "2022-11-15",
  "centerLetter": "f",
  "outerLetters": [
    "d",
    "g",
    "i",
    "l",
    "n",
    "o"
  ],
  "validLetters": [
    "f",
    "d",
    "g",
    "i",
    "l",
    "n",
    "o"
  ],
  "pangrams": [
    "flooding",
    "folding",
    "fondling"
  ],
  "answers": [
    "doff",
    "doffing",
    "fiddling",
    "fifing",
    "filing",
    "fill",
    "filling",
    "find",
    "finding",
    "fining",
    "fling",
    "flinging",
    "flog",
    "flogging",
    "flood",
    "flooding",
    "fogging",
    "foil",
    "foiling",
    "fold",
    "folding",
    "folio",
    "fond",
    "fondling",
    "food",
    "fool",
    "fooling",
    "golf",
    "golfing",
    "goof",
    "goofing",
    "infill",
    "infilling",
    "info",
    "offing"
  ],
  "id": 1668488400,
  "freeExpiration": 0,
  "editor": "Sam Ezersky"
}