{
  "displayWeekday": "Tuesday",
  "displayDate": "July 05, 2022",
  "printDate": "2022-07-05",
  "centerLetter": "c",
  "outerLetters": [
    "a",
    "b",
    "g",
    "i",
    "k",
    "n"
  ],
  "validLetters": [
    "c",
    "a",
    "b",
    "g",
    "i",
    "k",
    "n"
  ],
  "pangrams": [
    "backing"
  ],
  "answers": [
    "abaci",
    "aback",
    "acacia",
    "acai",
    "acing",
    "back",
    "backing",
    "banc",
    "cabana",
    "cabbing",
    "cabin",
    "caging",
    "caking",
    "cancan",
    "caning",
    "canna",
    "canning",
    "icing",
    "kick",
    "kickback",
    "kicking",
    "knack",
    "knickknack",
    "niacin",
    "nick",
    "nicking"
  ],
  "id": 1656993600,
  "freeExpiration": 0,
  "editor": "Sam Ezersky"
}