{
  "displayWeekday": "Tuesday",
  "displayDate": "April 12, 2022",
  "printDate": "2022-04-12",
  "centerLetter": "b",
  "outerLetters": [
    "a",
    "e",
    "l",
    "o",
    "v",
    "y"
  ],
  "validLetters": [
    "b",
    "a",
    "e",
    "l",
    "o",
    "v",
    "y"
  ],
  "pangrams": [
    "loveably",
    "volleyball"
  ],
  "answers": [
    "abbey",
    "able",
    "ably",
    "above",
    "baba",
    "babble",
    "babe",
    "babel",
    "baby",
    "bale",
    "ball",
    "ballboy",
    "baobab",
    "belay",
    "bell",
    "bellboy",
    "belle",
    "belly",
    "bevel",
    "bevy",
    "blab",
    "blabby",
    "blob",
    "blobby",
    "boba",
    "bobble",
    "bola",
    "boll",
    "bolo",
    "boob",
    "booboo",
    "booby",
    "eyeball",
    "label",
    "lobby",
    "lobe",
    "loblolly",
    "lobo",
    "lovable",
    "lovably",
    "loveable",
    "loveably",
    "obey",
    "oboe",
    "volleyball"
  ],
  "id": 1649736000,
  "freeExpiration": 0,
  "editor": "Sam Ezersky"
}