{
  "displayWeekday": "Monday",
  "displayDate": "March 24, 2025",
  "printDate": "2025-03-24",
  "centerLetter": "o",
  "outerLetters": [
    "a",
    "b",
    "d",
    "i",
    "l",
    "r"
  ],
  "validLetters": [
    "o",
    "a",
    "b",
    "d",
    "i",
    "l",
    "r"
  ],
  "pangrams": [
    "billboard"
  ],
  "answers": [
    "aboard",
    "aboil",
    "abroad",
    "adobo",
    "aioli",
    "arbor",
    "arborio",
    "ardor",
    "baobab",
    "barrio",
    "billboard",
    "blob",
    "blood",
    "boar",
    "board",
    "boba",
    "boil",
    "bola",
    "bold",
    "boll",
    "bollard",
    "bolo",
    "boob",
    "booboo",
    "boor",
    "brio",
    "broad",
    "broil",
    "brood",
    "dildo",
    "dodo",
    "doll",
    "dollar",
    "dolor",
    "doodad",
    "door",
    "dorado",
    "droid",
    "droll",
    "drool",
    "idol",
    "labor",
    "libido",
    "load",
    "lobo",
    "loll",
    "lord",
    "oddball",
    "odor",
    "olio",
    "oral",
    "radio",
    "railroad",
    "road",
    "roar",
    "roil",
    "roll",
    "rollbar",
    "rood"
  ],
  "id": 1742788800,
  "freeExpiration": 0,
  "editor": "Sam Ezersky"
}