{
  "displayWeekday": "Wednesday",
  "displayDate": "April 23, 2025",
  "printDate": "2025-04-23",
  "centerLetter": "u",
  "outerLetters": [
    "c",
    "d",
    "e",
    "i",
    "l",
    "t"
  ],
  "validLetters": [
    "u",
    "c",
    "d",
    "e",
    "i",
    "l",
    "t"
  ],
  "pangrams": [
    "ductile"
  ],
  "answers": [
    "cellule",
    "cellulite",
    "clue",
    "clued",
    "cuddle",
    "cuddled",
    "cued",
    "cull",
    "culled",
    "cult",
    "cultic",
    "cute",
    "cuticle",
    "cutie",
    "cutlet",
    "cuttle",
    "deduce",
    "deduced",
    "deduct",
    "deducted",
    "delude",
    "deluded",
    "deuce",
    "dilute",
    "diluted",
    "duct",
    "ducted",
    "ductile",
    "dude",
    "duel",
    "dueled",
    "duet",
    "duetted",
    "dulcet",
    "dull",
    "dulled",
    "educe",
    "educed",
    "elude",
    "eluded",
    "etude",
    "lettuce",
    "lieu",
    "lucid",
    "lull",
    "lulled",
    "lulu",
    "lute",
    "tulle",
    "tutee",
    "tutted",
    "tutti",
    "tutu",
    "utile"
  ],
  "id": 1745380800,
  "freeExpiration": 0,
  "editor": "Sam Ezersky"
}